ipyigv/__init__.py
ipyigv/_version.py
ipyigv/ipyigv.py
ipyigv/options.py
ipyigv/public_genomes.json
ipyigv/utils.py
ipyigv/labextension/package.json
ipyigv/labextension/static/138.93ff5122a91b7d500341.js
ipyigv/labextension/static/138.93ff5122a91b7d500341.js.LICENSE.txt
ipyigv/labextension/static/486.687c2e049f2160a9b3c3.js
ipyigv/labextension/static/486.687c2e049f2160a9b3c3.js.LICENSE.txt
ipyigv/labextension/static/908.f1b2c73f3f76bea7ca6d.js
ipyigv/labextension/static/remoteEntry.eea9b2feb2fb6ef9a43b.js
ipyigv/labextension/static/style.js
ipyigv/nbextension/extension.js
ipyigv/nbextension/index.js
ipyigv/nbextension/index.js.map
ipyigv/tests/__init__.py
ipyigv/tests/test.py
ipyigv-0.1.9.data/data/etc/jupyter/nbconfig/notebook.d/jupyter-igv.json
ipyigv-0.1.9.data/data/share/jupyter/labextensions/jupyter-igv/package.json
ipyigv-0.1.9.data/data/share/jupyter/labextensions/jupyter-igv/static/138.93ff5122a91b7d500341.js
ipyigv-0.1.9.data/data/share/jupyter/labextensions/jupyter-igv/static/138.93ff5122a91b7d500341.js.LICENSE.txt
ipyigv-0.1.9.data/data/share/jupyter/labextensions/jupyter-igv/static/486.687c2e049f2160a9b3c3.js
ipyigv-0.1.9.data/data/share/jupyter/labextensions/jupyter-igv/static/486.687c2e049f2160a9b3c3.js.LICENSE.txt
ipyigv-0.1.9.data/data/share/jupyter/labextensions/jupyter-igv/static/908.f1b2c73f3f76bea7ca6d.js
ipyigv-0.1.9.data/data/share/jupyter/labextensions/jupyter-igv/static/remoteEntry.eea9b2feb2fb6ef9a43b.js
ipyigv-0.1.9.data/data/share/jupyter/labextensions/jupyter-igv/static/style.js
ipyigv-0.1.9.data/data/share/jupyter/nbextensions/jupyter-igv/extension.js
ipyigv-0.1.9.data/data/share/jupyter/nbextensions/jupyter-igv/index.js
ipyigv-0.1.9.data/data/share/jupyter/nbextensions/jupyter-igv/index.js.map
ipyigv-0.1.9.dist-info/LICENSE
ipyigv-0.1.9.dist-info/METADATA
ipyigv-0.1.9.dist-info/WHEEL
ipyigv-0.1.9.dist-info/top_level.txt
ipyigv-0.1.9.dist-info/RECORD
